mrcfile/__init__.py
mrcfile/bzip2mrcfile.py
mrcfile/command_line.py
mrcfile/constants.py
mrcfile/dtypes.py
mrcfile/future_mrcfile.py
mrcfile/gzipmrcfile.py
mrcfile/load_functions.py
mrcfile/mrcfile.py
mrcfile/mrcinterpreter.py
mrcfile/mrcmemmap.py
mrcfile/mrcobject.py
mrcfile/utils.py
mrcfile/validator.py
mrcfile/version.py
mrcfile-1.5.4.dist-info/LICENSE.txt
mrcfile-1.5.4.dist-info/METADATA
mrcfile-1.5.4.dist-info/WHEEL
mrcfile-1.5.4.dist-info/entry_points.txt
mrcfile-1.5.4.dist-info/top_level.txt
mrcfile-1.5.4.dist-info/RECORD
